robot_plugin/__init__.py
robot_plugin/module.py
robot_plugin-0.3.dist-info/METADATA
robot_plugin-0.3.dist-info/WHEEL
robot_plugin-0.3.dist-info/top_level.txt
robot_plugin-0.3.dist-info/RECORD
