Metadata-Version: 2.1
Name: robot-plugin
Version: 0.3
Summary: 机器人插件依赖包
Author: NightMing
Author-email: 961880295@qq.com
Requires-Dist: requests
